{
  "content_hash": "55ed9b9917df0d1c10e03e35d6dbcc5607a586a8f5298c38d1bb6803d9dccd2a",
  "current_version": "20260618-f93d0d2ea67f",
  "dataset_id": "atlas-symbol-coverage",
  "disclaimer": "Read-only public metadata for Atlas coverage. Not investment advice.",
  "generated_at": "2026-06-18T06:13:24Z",
  "manifest_url": "https://atlas.freedomcore.io/datasets/atlas-authority-manifest.json",
  "name": "Atlas Symbol Coverage Index",
  "public_base": "https://atlas.freedomcore.io",
  "row_count": 175,
  "row_count_public": 175,
  "row_count_total": 226,
  "rows": [
    {
      "asset_class": "crypto",
      "context_as_of": "2026-06-14T05:00:03.768293+00:00",
      "daily_context_present": true,
      "public_note": "Crawlable Atlas symbol page backed by daily context metadata.",
      "quality_status": "persisted_atlas_wit_v2",
      "sitemap_lastmod": "2026-06-16",
      "source_count": 5,
      "symbol": "A7A5",
      "url": "https://atlas.freedomcore.io/stocks/A7A5/"
    },
    {
      "asset_class": "equity",
      "context_as_of": "2026-06-17T05:32:17.187331+00:00",
      "daily_context_present": true,
      "public_note": "Crawlable Atlas symbol page backed by daily context metadata.",
      "quality_status": "persisted_atlas_wit_v2",
      "sitemap_lastmod": "2026-06-16",
      "source_count": 4,
      "symbol": "AAPL",
      "url": "https://atlas.freedomcore.io/stocks/AAPL/"
    },
    {
      "asset_class": "crypto",
      "context_as_of": "2026-06-18T05:00:02.931124+00:00",
      "daily_context_present": true,
      "public_note": "Crawlable Atlas symbol page backed by daily context metadata.",
      "quality_status": "validated",
      "sitemap_lastmod": "2026-06-16",
      "source_count": 5,
      "symbol": "AAVE",
      "url": "https://atlas.freedomcore.io/stocks/AAVE/"
    },
    {
      "asset_class": "equity",
      "context_as_of": "2026-06-17T05:34:05.988740+00:00",
      "daily_context_present": true,
      "public_note": "Crawlable Atlas symbol page backed by daily context metadata.",
      "quality_status": "persisted_atlas_wit_v2",
      "sitemap_lastmod": "2026-06-16",
      "source_count": 4,
      "symbol": "ABNB",
      "url": "https://atlas.freedomcore.io/stocks/ABNB/"
    },
    {
      "asset_class": "crypto",
      "context_as_of": "2026-06-18T05:00:01.049922+00:00",
      "daily_context_present": true,
      "public_note": "Crawlable Atlas symbol page backed by daily context metadata.",
      "quality_status": "validated",
      "sitemap_lastmod": "2026-06-16",
      "source_count": 5,
      "symbol": "ADA",
      "url": "https://atlas.freedomcore.io/stocks/ADA/"
    },
    {
      "asset_class": "equity",
      "context_as_of": "2026-06-17T17:33:07.511217+00:00",
      "daily_context_present": true,
      "public_note": "Crawlable Atlas symbol page backed by daily context metadata.",
      "quality_status": "validated",
      "sitemap_lastmod": "2026-06-17",
      "source_count": 4,
      "symbol": "ADBE",
      "url": "https://atlas.freedomcore.io/stocks/ADBE/"
    },
    {
      "asset_class": "crypto",
      "context_as_of": "2026-06-18T05:01:01.948664+00:00",
      "daily_context_present": true,
      "public_note": "Crawlable Atlas symbol page backed by daily context metadata.",
      "quality_status": "validated",
      "sitemap_lastmod": "2026-06-16",
      "source_count": 5,
      "symbol": "ALGO",
      "url": "https://atlas.freedomcore.io/stocks/ALGO/"
    },
    {
      "asset_class": "equity",
      "context_as_of": "2026-06-17T05:32:35.658289+00:00",
      "daily_context_present": true,
      "public_note": "Crawlable Atlas symbol page backed by daily context metadata.",
      "quality_status": "validated",
      "sitemap_lastmod": "2026-06-16",
      "source_count": 4,
      "symbol": "AMD",
      "url": "https://atlas.freedomcore.io/stocks/AMD/"
    },
    {
      "asset_class": "equity",
      "context_as_of": "2026-06-18T05:01:23.755891+00:00",
      "daily_context_present": true,
      "public_note": "Crawlable Atlas symbol page backed by daily context metadata.",
      "quality_status": "validated",
      "sitemap_lastmod": "2026-06-16",
      "source_count": 4,
      "symbol": "AMZN",
      "url": "https://atlas.freedomcore.io/stocks/AMZN/"
    },
    {
      "asset_class": "crypto",
      "context_as_of": "2026-06-18T05:01:03.693509+00:00",
      "daily_context_present": true,
      "public_note": "Crawlable Atlas symbol page backed by daily context metadata.",
      "quality_status": "validated",
      "sitemap_lastmod": "2026-06-16",
      "source_count": 5,
      "symbol": "APT",
      "url": "https://atlas.freedomcore.io/stocks/APT/"
    },
    {
      "asset_class": "crypto",
      "context_as_of": "2026-06-18T05:01:05.282760+00:00",
      "daily_context_present": true,
      "public_note": "Crawlable Atlas symbol page backed by daily context metadata.",
      "quality_status": "validated",
      "sitemap_lastmod": "2026-06-16",
      "source_count": 4,
      "symbol": "ARB",
      "url": "https://atlas.freedomcore.io/stocks/ARB/"
    },
    {
      "asset_class": "crypto",
      "context_as_of": "2026-06-18T05:00:02.260864+00:00",
      "daily_context_present": true,
      "public_note": "Crawlable Atlas symbol page backed by daily context metadata.",
      "quality_status": "validated",
      "sitemap_lastmod": "2026-06-16",
      "source_count": 5,
      "symbol": "ASTER",
      "url": "https://atlas.freedomcore.io/stocks/ASTER/"
    },
    {
      "asset_class": "crypto",
      "context_as_of": "2026-06-18T05:00:02.950347+00:00",
      "daily_context_present": true,
      "public_note": "Crawlable Atlas symbol page backed by daily context metadata.",
      "quality_status": "validated",
      "sitemap_lastmod": "2026-06-16",
      "source_count": 5,
      "symbol": "ATOM",
      "url": "https://atlas.freedomcore.io/stocks/ATOM/"
    },
    {
      "asset_class": "crypto",
      "context_as_of": "2026-06-18T05:00:01.693326+00:00",
      "daily_context_present": true,
      "public_note": "Crawlable Atlas symbol page backed by daily context metadata.",
      "quality_status": "validated",
      "sitemap_lastmod": "2026-06-16",
      "source_count": 5,
      "symbol": "AVAX",
      "url": "https://atlas.freedomcore.io/stocks/AVAX/"
    },
    {
      "asset_class": "equity",
      "context_as_of": "2026-06-17T17:27:21.847971+00:00",
      "daily_context_present": true,
      "public_note": "Crawlable Atlas symbol page backed by daily context metadata.",
      "quality_status": "validated",
      "sitemap_lastmod": "2026-06-17",
      "source_count": 4,
      "symbol": "AVGO",
      "url": "https://atlas.freedomcore.io/stocks/AVGO/"
    },
    {
      "asset_class": "equity",
      "context_as_of": "2026-06-18T05:02:58.630500+00:00",
      "daily_context_present": true,
      "public_note": "Crawlable Atlas symbol page backed by daily context metadata.",
      "quality_status": "validated",
      "sitemap_lastmod": "2026-06-17",
      "source_count": 4,
      "symbol": "BA",
      "url": "https://atlas.freedomcore.io/stocks/BA/"
    },
    {
      "asset_class": "equity",
      "context_as_of": "2026-06-17T17:42:41.354092+00:00",
      "daily_context_present": true,
      "public_note": "Crawlable Atlas symbol page backed by daily context metadata.",
      "quality_status": "validated",
      "sitemap_lastmod": "2026-06-17",
      "source_count": 4,
      "symbol": "BAC",
      "url": "https://atlas.freedomcore.io/stocks/BAC/"
    },
    {
      "asset_class": "crypto",
      "context_as_of": "2026-06-18T05:00:03.131272+00:00",
      "daily_context_present": true,
      "public_note": "Crawlable Atlas symbol page backed by daily context metadata.",
      "quality_status": "validated",
      "sitemap_lastmod": "2026-06-16",
      "source_count": 4,
      "symbol": "BCAP",
      "url": "https://atlas.freedomcore.io/stocks/BCAP/"
    },
    {
      "asset_class": "crypto",
      "context_as_of": "2026-06-18T05:00:01.298222+00:00",
      "daily_context_present": true,
      "public_note": "Crawlable Atlas symbol page backed by daily context metadata.",
      "quality_status": "validated",
      "sitemap_lastmod": "2026-06-16",
      "source_count": 5,
      "symbol": "BCH",
      "url": "https://atlas.freedomcore.io/stocks/BCH/"
    },
    {
      "asset_class": "crypto",
      "context_as_of": "2026-06-18T05:01:03.592567+00:00",
      "daily_context_present": true,
      "public_note": "Crawlable Atlas symbol page backed by daily context metadata.",
      "quality_status": "validated",
      "sitemap_lastmod": "2026-06-16",
      "source_count": 5,
      "symbol": "BDX",
      "url": "https://atlas.freedomcore.io/stocks/BDX/"
    },
    {
      "asset_class": "crypto",
      "context_as_of": "2026-06-18T05:00:02.375370+00:00",
      "daily_context_present": true,
      "public_note": "Crawlable Atlas symbol page backed by daily context metadata.",
      "quality_status": "validated",
      "sitemap_lastmod": "2026-06-16",
      "source_count": 5,
      "symbol": "BEAT",
      "url": "https://atlas.freedomcore.io/stocks/BEAT/"
    },
    {
      "asset_class": "crypto",
      "context_as_of": "2026-06-18T05:00:02.742659+00:00",
      "daily_context_present": true,
      "public_note": "Crawlable Atlas symbol page backed by daily context metadata.",
      "quality_status": "validated",
      "sitemap_lastmod": "2026-06-16",
      "source_count": 4,
      "symbol": "BFUSD",
      "url": "https://atlas.freedomcore.io/stocks/BFUSD/"
    },
    {
      "asset_class": "crypto",
      "context_as_of": "2026-06-18T05:00:02.802802+00:00",
      "daily_context_present": true,
      "public_note": "Crawlable Atlas symbol page backed by daily context metadata.",
      "quality_status": "validated",
      "sitemap_lastmod": "2026-06-16",
      "source_count": 5,
      "symbol": "BGB",
      "url": "https://atlas.freedomcore.io/stocks/BGB/"
    },
    {
      "asset_class": "crypto",
      "context_as_of": "2026-06-18T05:01:03.533587+00:00",
      "daily_context_present": true,
      "public_note": "Crawlable Atlas symbol page backed by daily context metadata.",
      "quality_status": "validated",
      "sitemap_lastmod": "2026-06-16",
      "source_count": 3,
      "symbol": "BIANRENSHENG",
      "url": "https://atlas.freedomcore.io/stocks/BIANRENSHENG/"
    },
    {
      "asset_class": "crypto",
      "context_as_of": "2026-06-18T05:00:00.782286+00:00",
      "daily_context_present": true,
      "public_note": "Crawlable Atlas symbol page backed by daily context metadata.",
      "quality_status": "validated",
      "sitemap_lastmod": "2026-06-16",
      "source_count": 5,
      "symbol": "BNB",
      "url": "https://atlas.freedomcore.io/stocks/BNB/"
    },
    {
      "asset_class": "equity",
      "context_as_of": "2026-06-18T05:02:09.452372+00:00",
      "daily_context_present": true,
      "public_note": "Crawlable Atlas symbol page backed by daily context metadata.",
      "quality_status": "validated",
      "sitemap_lastmod": "2026-06-17",
      "source_count": 4,
      "symbol": "BRK-B",
      "url": "https://atlas.freedomcore.io/stocks/BRK-B/"
    },
    {
      "asset_class": "crypto",
      "context_as_of": "2026-06-18T05:00:00.688933+00:00",
      "daily_context_present": true,
      "public_note": "Crawlable Atlas symbol page backed by daily context metadata.",
      "quality_status": "validated",
      "sitemap_lastmod": "2026-06-16",
      "source_count": 5,
      "symbol": "BTC",
      "url": "https://atlas.freedomcore.io/stocks/BTC/"
    },
    {
      "asset_class": "crypto",
      "context_as_of": "2026-06-18T05:00:01.925172+00:00",
      "daily_context_present": true,
      "public_note": "Crawlable Atlas symbol page backed by daily context metadata.",
      "quality_status": "validated",
      "sitemap_lastmod": "2026-06-16",
      "source_count": 5,
      "symbol": "BUIDL",
      "url": "https://atlas.freedomcore.io/stocks/BUIDL/"
    },
    {
      "asset_class": "equity",
      "context_as_of": "2026-06-18T05:03:01.196041+00:00",
      "daily_context_present": true,
      "public_note": "Crawlable Atlas symbol page backed by daily context metadata.",
      "quality_status": "validated",
      "sitemap_lastmod": "2026-06-16",
      "source_count": 4,
      "symbol": "CAT",
      "url": "https://atlas.freedomcore.io/stocks/CAT/"
    },
    {
      "asset_class": "crypto",
      "context_as_of": "2026-06-18T05:00:01.099812+00:00",
      "daily_context_present": true,
      "public_note": "Crawlable Atlas symbol page backed by daily context metadata.",
      "quality_status": "validated",
      "sitemap_lastmod": "2026-06-16",
      "source_count": 5,
      "symbol": "CC",
      "url": "https://atlas.freedomcore.io/stocks/CC/"
    },
    {
      "asset_class": "equity",
      "context_as_of": "2026-06-18T05:02:16.306590+00:00",
      "daily_context_present": true,
      "public_note": "Crawlable Atlas symbol page backed by daily context metadata.",
      "quality_status": "persisted_atlas_wit_v2",
      "sitemap_lastmod": "2026-06-16",
      "source_count": 4,
      "symbol": "COIN",
      "url": "https://atlas.freedomcore.io/stocks/COIN/"
    },
    {
      "asset_class": "commodity",
      "context_as_of": "2026-06-18T05:03:37.979257+00:00",
      "daily_context_present": true,
      "public_note": "Crawlable Atlas symbol page backed by daily context metadata.",
      "quality_status": "persisted_atlas_wit_v2",
      "sitemap_lastmod": "2026-06-16",
      "source_count": 3,
      "symbol": "COPPER",
      "url": "https://atlas.freedomcore.io/stocks/COPPER/"
    },
    {
      "asset_class": "equity",
      "context_as_of": "2026-06-18T05:02:27.933349+00:00",
      "daily_context_present": true,
      "public_note": "Crawlable Atlas symbol page backed by daily context metadata.",
      "quality_status": "validated",
      "sitemap_lastmod": "2026-06-16",
      "source_count": 4,
      "symbol": "COST",
      "url": "https://atlas.freedomcore.io/stocks/COST/"
    },
    {
      "asset_class": "equity",
      "context_as_of": "2026-06-18T05:01:43.475111+00:00",
      "daily_context_present": true,
      "public_note": "Crawlable Atlas symbol page backed by daily context metadata.",
      "quality_status": "persisted_atlas_wit_v2",
      "sitemap_lastmod": "2026-06-16",
      "source_count": 4,
      "symbol": "CRM",
      "url": "https://atlas.freedomcore.io/stocks/CRM/"
    },
    {
      "asset_class": "crypto",
      "context_as_of": "2026-06-18T05:00:01.840907+00:00",
      "daily_context_present": true,
      "public_note": "Crawlable Atlas symbol page backed by daily context metadata.",
      "quality_status": "validated",
      "sitemap_lastmod": "2026-06-16",
      "source_count": 5,
      "symbol": "CRO",
      "url": "https://atlas.freedomcore.io/stocks/CRO/"
    },
    {
      "asset_class": "equity",
      "context_as_of": "2026-06-18T05:02:51.422067+00:00",
      "daily_context_present": true,
      "public_note": "Crawlable Atlas symbol page backed by daily context metadata.",
      "quality_status": "persisted_atlas_wit_v2",
      "sitemap_lastmod": "2026-06-16",
      "source_count": 4,
      "symbol": "CVX",
      "url": "https://atlas.freedomcore.io/stocks/CVX/"
    },
    {
      "asset_class": "crypto",
      "context_as_of": "2026-06-18T05:00:01.327390+00:00",
      "daily_context_present": true,
      "public_note": "Crawlable Atlas symbol page backed by daily context metadata.",
      "quality_status": "validated",
      "sitemap_lastmod": "2026-06-16",
      "source_count": 5,
      "symbol": "DAI",
      "url": "https://atlas.freedomcore.io/stocks/DAI/"
    },
    {
      "asset_class": "index",
      "context_as_of": "2026-06-18T05:03:52.780336+00:00",
      "daily_context_present": true,
      "public_note": "Crawlable Atlas symbol page backed by daily context metadata.",
      "quality_status": "persisted_atlas_wit_v2",
      "sitemap_lastmod": "2026-06-16",
      "source_count": 2,
      "symbol": "DE40",
      "url": "https://atlas.freedomcore.io/stocks/DE40/"
    },
    {
      "asset_class": "crypto",
      "context_as_of": "2026-06-18T05:01:01.899455+00:00",
      "daily_context_present": true,
      "public_note": "Crawlable Atlas symbol page backed by daily context metadata.",
      "quality_status": "validated",
      "sitemap_lastmod": "2026-06-16",
      "source_count": 4,
      "symbol": "DEXE",
      "url": "https://atlas.freedomcore.io/stocks/DEXE/"
    },
    {
      "asset_class": "equity",
      "context_as_of": "2026-06-18T05:02:53.723443+00:00",
      "daily_context_present": true,
      "public_note": "Crawlable Atlas symbol page backed by daily context metadata.",
      "quality_status": "validated",
      "sitemap_lastmod": "2026-06-17",
      "source_count": 4,
      "symbol": "DIS",
      "url": "https://atlas.freedomcore.io/stocks/DIS/"
    },
    {
      "asset_class": "crypto",
      "context_as_of": "2026-06-18T05:00:00.933053+00:00",
      "daily_context_present": true,
      "public_note": "Crawlable Atlas symbol page backed by daily context metadata.",
      "quality_status": "validated",
      "sitemap_lastmod": "2026-06-16",
      "source_count": 5,
      "symbol": "DOGE",
      "url": "https://atlas.freedomcore.io/stocks/DOGE/"
    },
    {
      "asset_class": "crypto",
      "context_as_of": "2026-06-18T05:00:02.300171+00:00",
      "daily_context_present": true,
      "public_note": "Crawlable Atlas symbol page backed by daily context metadata.",
      "quality_status": "validated",
      "sitemap_lastmod": "2026-06-16",
      "source_count": 5,
      "symbol": "DOT",
      "url": "https://atlas.freedomcore.io/stocks/DOT/"
    },
    {
      "asset_class": "index",
      "context_as_of": "2026-06-18T05:03:49.422861+00:00",
      "daily_context_present": true,
      "public_note": "Crawlable Atlas symbol page backed by daily context metadata.",
      "quality_status": "persisted_atlas_wit_v2",
      "sitemap_lastmod": "2026-06-16",
      "source_count": 2,
      "symbol": "DXY",
      "url": "https://atlas.freedomcore.io/stocks/DXY/"
    },
    {
      "asset_class": "crypto",
      "context_as_of": "2026-06-18T05:01:02.027099+00:00",
      "daily_context_present": true,
      "public_note": "Crawlable Atlas symbol page backed by daily context metadata.",
      "quality_status": "validated",
      "sitemap_lastmod": "2026-06-16",
      "source_count": 5,
      "symbol": "ENA",
      "url": "https://atlas.freedomcore.io/stocks/ENA/"
    },
    {
      "asset_class": "crypto",
      "context_as_of": "2026-06-18T05:00:02.891707+00:00",
      "daily_context_present": true,
      "public_note": "Crawlable Atlas symbol page backed by daily context metadata.",
      "quality_status": "validated",
      "sitemap_lastmod": "2026-06-16",
      "source_count": 4,
      "symbol": "ETC",
      "url": "https://atlas.freedomcore.io/stocks/ETC/"
    },
    {
      "asset_class": "crypto",
      "context_as_of": "2026-06-18T05:00:00.731261+00:00",
      "daily_context_present": true,
      "public_note": "Crawlable Atlas symbol page backed by daily context metadata.",
      "quality_status": "validated",
      "sitemap_lastmod": "2026-06-16",
      "source_count": 5,
      "symbol": "ETH",
      "url": "https://atlas.freedomcore.io/stocks/ETH/"
    },
    {
      "asset_class": "forex",
      "context_as_of": "2026-06-18T05:03:28.610169+00:00",
      "daily_context_present": true,
      "public_note": "Crawlable Atlas symbol page backed by daily context metadata.",
      "quality_status": "persisted_atlas_wit_v2",
      "sitemap_lastmod": "2026-06-16",
      "source_count": 5,
      "symbol": "EURUSD",
      "url": "https://atlas.freedomcore.io/stocks/EURUSD/"
    },
    {
      "asset_class": "crypto",
      "context_as_of": "2026-06-18T05:00:03.100147+00:00",
      "daily_context_present": true,
      "public_note": "Crawlable Atlas symbol page backed by daily context metadata.",
      "quality_status": "validated",
      "sitemap_lastmod": "2026-06-16",
      "source_count": 5,
      "symbol": "EUTBL",
      "url": "https://atlas.freedomcore.io/stocks/EUTBL/"
    },
    {
      "asset_class": "crypto",
      "context_as_of": "2026-06-18T05:00:00.884272+00:00",
      "daily_context_present": true,
      "public_note": "Crawlable Atlas symbol page backed by daily context metadata.",
      "quality_status": "validated",
      "sitemap_lastmod": "2026-06-16",
      "source_count": 5,
      "symbol": "FIGRHELOC",
      "url": "https://atlas.freedomcore.io/stocks/FIGRHELOC/"
    },
    {
      "asset_class": "crypto",
      "context_as_of": "2026-06-18T05:01:03.561301+00:00",
      "daily_context_present": true,
      "public_note": "Crawlable Atlas symbol page backed by daily context metadata.",
      "quality_status": "validated",
      "sitemap_lastmod": "2026-06-16",
      "source_count": 5,
      "symbol": "FIL",
      "url": "https://atlas.freedomcore.io/stocks/FIL/"
    },
    {
      "asset_class": "crypto",
      "context_as_of": "2026-06-18T05:01:03.510068+00:00",
      "daily_context_present": true,
      "public_note": "Crawlable Atlas symbol page backed by daily context metadata.",
      "quality_status": "validated",
      "sitemap_lastmod": "2026-06-16",
      "source_count": 5,
      "symbol": "FLR",
      "url": "https://atlas.freedomcore.io/stocks/FLR/"
    },
    {
      "asset_class": "forex",
      "context_as_of": "2026-06-18T05:03:30.444182+00:00",
      "daily_context_present": true,
      "public_note": "Crawlable Atlas symbol page backed by daily context metadata.",
      "quality_status": "persisted_atlas_wit_v2",
      "sitemap_lastmod": "2026-06-16",
      "source_count": 5,
      "symbol": "GBPUSD",
      "url": "https://atlas.freedomcore.io/stocks/GBPUSD/"
    },
    {
      "asset_class": "equity",
      "context_as_of": "2026-06-18T05:03:03.608084+00:00",
      "daily_context_present": true,
      "public_note": "Crawlable Atlas symbol page backed by daily context metadata.",
      "quality_status": "validated",
      "sitemap_lastmod": "2026-06-16",
      "source_count": 4,
      "symbol": "GE",
      "url": "https://atlas.freedomcore.io/stocks/GE/"
    },
    {
      "asset_class": "crypto",
      "context_as_of": "2026-06-18T05:01:03.657682+00:00",
      "daily_context_present": true,
      "public_note": "Crawlable Atlas symbol page backed by daily context metadata.",
      "quality_status": "validated",
      "sitemap_lastmod": "2026-06-16",
      "source_count": 5,
      "symbol": "GHO",
      "url": "https://atlas.freedomcore.io/stocks/GHO/"
    },
    {
      "asset_class": "commodity",
      "context_as_of": "2026-06-18T05:03:34.168183+00:00",
      "daily_context_present": true,
      "public_note": "Crawlable Atlas symbol page backed by daily context metadata.",
      "quality_status": "persisted_atlas_wit_v2",
      "sitemap_lastmod": "2026-06-16",
      "source_count": 3,
      "symbol": "GOLD",
      "url": "https://atlas.freedomcore.io/stocks/GOLD/"
    },
    {
      "asset_class": "equity",
      "context_as_of": "2026-06-17T05:32:27.467922+00:00",
      "daily_context_present": true,
      "public_note": "Crawlable Atlas symbol page backed by daily context metadata.",
      "quality_status": "persisted_atlas_wit_v2",
      "sitemap_lastmod": "2026-06-16",
      "source_count": 4,
      "symbol": "GOOGL",
      "url": "https://atlas.freedomcore.io/stocks/GOOGL/"
    },
    {
      "asset_class": "equity",
      "context_as_of": "2026-06-17T17:45:49.166676+00:00",
      "daily_context_present": true,
      "public_note": "Crawlable Atlas symbol page backed by daily context metadata.",
      "quality_status": "validated",
      "sitemap_lastmod": "2026-06-17",
      "source_count": 4,
      "symbol": "GS",
      "url": "https://atlas.freedomcore.io/stocks/GS/"
    },
    {
      "asset_class": "crypto",
      "context_as_of": "2026-06-18T05:01:02.062882+00:00",
      "daily_context_present": true,
      "public_note": "Crawlable Atlas symbol page backed by daily context metadata.",
      "quality_status": "validated",
      "sitemap_lastmod": "2026-06-16",
      "source_count": 4,
      "symbol": "GT",
      "url": "https://atlas.freedomcore.io/stocks/GT/"
    },
    {
      "asset_class": "crypto",
      "context_as_of": "2026-06-18T05:00:03.312111+00:00",
      "daily_context_present": true,
      "public_note": "Crawlable Atlas symbol page backed by daily context metadata.",
      "quality_status": "validated",
      "sitemap_lastmod": "2026-06-16",
      "source_count": 5,
      "symbol": "H",
      "url": "https://atlas.freedomcore.io/stocks/H/"
    },
    {
      "asset_class": "crypto",
      "context_as_of": "2026-06-12T05:01:04.088671+00:00",
      "daily_context_present": true,
      "public_note": "Crawlable Atlas symbol page backed by daily context metadata.",
      "quality_status": "persisted_atlas_wit_v2",
      "sitemap_lastmod": "2026-06-16",
      "source_count": 5,
      "symbol": "HASH",
      "url": "https://atlas.freedomcore.io/stocks/HASH/"
    },
    {
      "asset_class": "crypto",
      "context_as_of": "2026-06-18T05:00:01.382225+00:00",
      "daily_context_present": true,
      "public_note": "Crawlable Atlas symbol page backed by daily context metadata.",
      "quality_status": "validated",
      "sitemap_lastmod": "2026-06-16",
      "source_count": 5,
      "symbol": "HBAR",
      "url": "https://atlas.freedomcore.io/stocks/HBAR/"
    },
    {
      "asset_class": "equity",
      "context_as_of": "2026-06-18T05:02:30.227070+00:00",
      "daily_context_present": true,
      "public_note": "Crawlable Atlas symbol page backed by daily context metadata.",
      "quality_status": "persisted_atlas_wit_v2",
      "sitemap_lastmod": "2026-06-16",
      "source_count": 4,
      "symbol": "HD",
      "url": "https://atlas.freedomcore.io/stocks/HD/"
    },
    {
      "asset_class": "equity",
      "context_as_of": "2026-06-18T05:02:18.620621+00:00",
      "daily_context_present": true,
      "public_note": "Crawlable Atlas symbol page backed by daily context metadata.",
      "quality_status": "validated",
      "sitemap_lastmod": "2026-06-17",
      "source_count": 4,
      "symbol": "HOOD",
      "url": "https://atlas.freedomcore.io/stocks/HOOD/"
    },
    {
      "asset_class": "crypto",
      "context_as_of": "2026-06-18T05:00:02.531036+00:00",
      "daily_context_present": true,
      "public_note": "Crawlable Atlas symbol page backed by daily context metadata.",
      "quality_status": "validated",
      "sitemap_lastmod": "2026-06-16",
      "source_count": 5,
      "symbol": "HTX",
      "url": "https://atlas.freedomcore.io/stocks/HTX/"
    },
    {
      "asset_class": "crypto",
      "context_as_of": "2026-06-18T05:00:00.910483+00:00",
      "daily_context_present": true,
      "public_note": "Crawlable Atlas symbol page backed by daily context metadata.",
      "quality_status": "validated",
      "sitemap_lastmod": "2026-06-16",
      "source_count": 5,
      "symbol": "HYPE",
      "url": "https://atlas.freedomcore.io/stocks/HYPE/"
    },
    {
      "asset_class": "crypto",
      "context_as_of": "2026-06-18T05:00:02.635220+00:00",
      "daily_context_present": true,
      "public_note": "Crawlable Atlas symbol page backed by daily context metadata.",
      "quality_status": "validated",
      "sitemap_lastmod": "2026-06-16",
      "source_count": 5,
      "symbol": "ICP",
      "url": "https://atlas.freedomcore.io/stocks/ICP/"
    },
    {
      "asset_class": "crypto",
      "context_as_of": "2026-06-14T05:00:03.576881+00:00",
      "daily_context_present": true,
      "public_note": "Crawlable Atlas symbol page backed by daily context metadata.",
      "quality_status": "persisted_atlas_wit_v2",
      "sitemap_lastmod": "2026-06-16",
      "source_count": 5,
      "symbol": "INJ",
      "url": "https://atlas.freedomcore.io/stocks/INJ/"
    },
    {
      "asset_class": "equity",
      "context_as_of": "2026-06-18T05:01:34.015810+00:00",
      "daily_context_present": true,
      "public_note": "Crawlable Atlas symbol page backed by daily context metadata.",
      "quality_status": "validated",
      "sitemap_lastmod": "2026-06-16",
      "source_count": 4,
      "symbol": "INTC",
      "url": "https://atlas.freedomcore.io/stocks/INTC/"
    },
    {
      "asset_class": "crypto",
      "context_as_of": "2026-06-18T05:01:03.488889+00:00",
      "daily_context_present": true,
      "public_note": "Crawlable Atlas symbol page backed by daily context metadata.",
      "quality_status": "validated",
      "sitemap_lastmod": "2026-06-16",
      "source_count": 4,
      "symbol": "JAAA",
      "url": "https://atlas.freedomcore.io/stocks/JAAA/"
    },
    {
      "asset_class": "equity",
      "context_as_of": "2026-06-18T05:02:42.082040+00:00",
      "daily_context_present": true,
      "public_note": "Crawlable Atlas symbol page backed by daily context metadata.",
      "quality_status": "validated",
      "sitemap_lastmod": "2026-06-16",
      "source_count": 4,
      "symbol": "JNJ",
      "url": "https://atlas.freedomcore.io/stocks/JNJ/"
    },
    {
      "asset_class": "index",
      "context_as_of": "2026-06-18T05:03:54.452659+00:00",
      "daily_context_present": true,
      "public_note": "Crawlable Atlas symbol page backed by daily context metadata.",
      "quality_status": "validated",
      "sitemap_lastmod": "2026-06-16",
      "source_count": 2,
      "symbol": "JP225",
      "url": "https://atlas.freedomcore.io/stocks/JP225/"
    },
    {
      "asset_class": "equity",
      "context_as_of": "2026-06-17T17:36:24.654219+00:00",
      "daily_context_present": true,
      "public_note": "Crawlable Atlas symbol page backed by daily context metadata.",
      "quality_status": "validated",
      "sitemap_lastmod": "2026-06-17",
      "source_count": 4,
      "symbol": "JPM",
      "url": "https://atlas.freedomcore.io/stocks/JPM/"
    },
    {
      "asset_class": "crypto",
      "context_as_of": "2026-06-18T05:01:03.547901+00:00",
      "daily_context_present": true,
      "public_note": "Crawlable Atlas symbol page backed by daily context metadata.",
      "quality_status": "validated",
      "sitemap_lastmod": "2026-06-16",
      "source_count": 5,
      "symbol": "JST",
      "url": "https://atlas.freedomcore.io/stocks/JST/"
    },
    {
      "asset_class": "crypto",
      "context_as_of": "2026-06-18T05:01:01.872130+00:00",
      "daily_context_present": true,
      "public_note": "Crawlable Atlas symbol page backed by daily context metadata.",
      "quality_status": "validated",
      "sitemap_lastmod": "2026-06-16",
      "source_count": 4,
      "symbol": "JTRSY",
      "url": "https://atlas.freedomcore.io/stocks/JTRSY/"
    },
    {
      "asset_class": "crypto",
      "context_as_of": "2026-06-18T05:01:03.578683+00:00",
      "daily_context_present": true,
      "public_note": "Crawlable Atlas symbol page backed by daily context metadata.",
      "quality_status": "validated",
      "sitemap_lastmod": "2026-06-16",
      "source_count": 4,
      "symbol": "JUP",
      "url": "https://atlas.freedomcore.io/stocks/JUP/"
    },
    {
      "asset_class": "crypto",
      "context_as_of": "2026-06-18T05:01:01.825946+00:00",
      "daily_context_present": true,
      "public_note": "Crawlable Atlas symbol page backed by daily context metadata.",
      "quality_status": "validated",
      "sitemap_lastmod": "2026-06-16",
      "source_count": 5,
      "symbol": "KAS",
      "url": "https://atlas.freedomcore.io/stocks/KAS/"
    },
    {
      "asset_class": "crypto",
      "context_as_of": "2026-06-18T05:00:03.265495+00:00",
      "daily_context_present": true,
      "public_note": "Crawlable Atlas symbol page backed by daily context metadata.",
      "quality_status": "validated",
      "sitemap_lastmod": "2026-06-16",
      "source_count": 4,
      "symbol": "KCS",
      "url": "https://atlas.freedomcore.io/stocks/KCS/"
    },
    {
      "asset_class": "crypto",
      "context_as_of": "2026-06-18T05:00:01.427074+00:00",
      "daily_context_present": true,
      "public_note": "Crawlable Atlas symbol page backed by daily context metadata.",
      "quality_status": "validated",
      "sitemap_lastmod": "2026-06-16",
      "source_count": 5,
      "symbol": "LAB",
      "url": "https://atlas.freedomcore.io/stocks/LAB/"
    },
    {
      "asset_class": "crypto",
      "context_as_of": "2026-06-18T05:00:00.977177+00:00",
      "daily_context_present": true,
      "public_note": "Crawlable Atlas symbol page backed by daily context metadata.",
      "quality_status": "validated",
      "sitemap_lastmod": "2026-06-16",
      "source_count": 5,
      "symbol": "LEO",
      "url": "https://atlas.freedomcore.io/stocks/LEO/"
    },
    {
      "asset_class": "crypto",
      "context_as_of": "2026-06-18T05:00:01.175504+00:00",
      "daily_context_present": true,
      "public_note": "Crawlable Atlas symbol page backed by daily context metadata.",
      "quality_status": "validated",
      "sitemap_lastmod": "2026-06-16",
      "source_count": 5,
      "symbol": "LINK",
      "url": "https://atlas.freedomcore.io/stocks/LINK/"
    },
    {
      "asset_class": "equity",
      "context_as_of": "2026-06-18T05:02:46.812941+00:00",
      "daily_context_present": true,
      "public_note": "Crawlable Atlas symbol page backed by daily context metadata.",
      "quality_status": "validated",
      "sitemap_lastmod": "2026-06-17",
      "source_count": 4,
      "symbol": "LLY",
      "url": "https://atlas.freedomcore.io/stocks/LLY/"
    },
    {
      "asset_class": "crypto",
      "context_as_of": "2026-06-18T05:00:01.408426+00:00",
      "daily_context_present": true,
      "public_note": "Crawlable Atlas symbol page backed by daily context metadata.",
      "quality_status": "validated",
      "sitemap_lastmod": "2026-06-16",
      "source_count": 5,
      "symbol": "LTC",
      "url": "https://atlas.freedomcore.io/stocks/LTC/"
    },
    {
      "asset_class": "crypto",
      "context_as_of": "2026-06-18T05:00:01.359278+00:00",
      "daily_context_present": true,
      "public_note": "Crawlable Atlas symbol page backed by daily context metadata.",
      "quality_status": "validated",
      "sitemap_lastmod": "2026-06-16",
      "source_count": 5,
      "symbol": "M",
      "url": "https://atlas.freedomcore.io/stocks/M/"
    },
    {
      "asset_class": "equity",
      "context_as_of": "2026-06-17T05:33:11.158504+00:00",
      "daily_context_present": true,
      "public_note": "Crawlable Atlas symbol page backed by daily context metadata.",
      "quality_status": "validated",
      "sitemap_lastmod": "2026-06-16",
      "source_count": 4,
      "symbol": "MA",
      "url": "https://atlas.freedomcore.io/stocks/MA/"
    },
    {
      "asset_class": "equity",
      "context_as_of": "2026-06-18T05:02:34.820298+00:00",
      "daily_context_present": true,
      "public_note": "Crawlable Atlas symbol page backed by daily context metadata.",
      "quality_status": "persisted_atlas_wit_v2",
      "sitemap_lastmod": "2026-06-16",
      "source_count": 4,
      "symbol": "MCD",
      "url": "https://atlas.freedomcore.io/stocks/MCD/"
    },
    {
      "asset_class": "equity",
      "context_as_of": "2026-06-17T05:32:31.732091+00:00",
      "daily_context_present": true,
      "public_note": "Crawlable Atlas symbol page backed by daily context metadata.",
      "quality_status": "validated",
      "sitemap_lastmod": "2026-06-16",
      "source_count": 4,
      "symbol": "META",
      "url": "https://atlas.freedomcore.io/stocks/META/"
    },
    {
      "asset_class": "crypto",
      "context_as_of": "2026-06-18T05:00:02.160147+00:00",
      "daily_context_present": true,
      "public_note": "Crawlable Atlas symbol page backed by daily context metadata.",
      "quality_status": "validated",
      "sitemap_lastmod": "2026-06-16",
      "source_count": 5,
      "symbol": "MNT",
      "url": "https://atlas.freedomcore.io/stocks/MNT/"
    },
    {
      "asset_class": "crypto",
      "context_as_of": "2026-06-18T05:00:02.772571+00:00",
      "daily_context_present": true,
      "public_note": "Crawlable Atlas symbol page backed by daily context metadata.",
      "quality_status": "validated",
      "sitemap_lastmod": "2026-06-16",
      "source_count": 5,
      "symbol": "MORPHO",
      "url": "https://atlas.freedomcore.io/stocks/MORPHO/"
    },
    {
      "asset_class": "equity",
      "context_as_of": "2026-06-17T17:50:44.045141+00:00",
      "daily_context_present": true,
      "public_note": "Crawlable Atlas symbol page backed by daily context metadata.",
      "quality_status": "validated",
      "sitemap_lastmod": "2026-06-17",
      "source_count": 4,
      "symbol": "MS",
      "url": "https://atlas.freedomcore.io/stocks/MS/"
    },
    {
      "asset_class": "equity",
      "context_as_of": "2026-06-18T05:01:18.453861+00:00",
      "daily_context_present": true,
      "public_note": "Crawlable Atlas symbol page backed by daily context metadata.",
      "quality_status": "validated",
      "sitemap_lastmod": "2026-06-17",
      "source_count": 4,
      "symbol": "MSFT",
      "url": "https://atlas.freedomcore.io/stocks/MSFT/"
    },
    {
      "asset_class": "equity",
      "context_as_of": "2026-06-18T05:01:40.951691+00:00",
      "daily_context_present": true,
      "public_note": "Crawlable Atlas symbol page backed by daily context metadata.",
      "quality_status": "persisted_atlas_wit_v2",
      "sitemap_lastmod": "2026-06-16",
      "source_count": 4,
      "symbol": "MU",
      "url": "https://atlas.freedomcore.io/stocks/MU/"
    },
    {
      "asset_class": "crypto",
      "context_as_of": "2026-06-18T05:00:01.495747+00:00",
      "daily_context_present": true,
      "public_note": "Crawlable Atlas symbol page backed by daily context metadata.",
      "quality_status": "validated",
      "sitemap_lastmod": "2026-06-16",
      "source_count": 5,
      "symbol": "NEAR",
      "url": "https://atlas.freedomcore.io/stocks/NEAR/"
    },
    {
      "asset_class": "crypto",
      "context_as_of": "2026-06-18T05:01:02.010008+00:00",
      "daily_context_present": true,
      "public_note": "Crawlable Atlas symbol page backed by daily context metadata.",
      "quality_status": "validated",
      "sitemap_lastmod": "2026-06-16",
      "source_count": 5,
      "symbol": "NEXO",
      "url": "https://atlas.freedomcore.io/stocks/NEXO/"
    },
    {
      "asset_class": "equity",
      "context_as_of": "2026-06-17T05:33:49.038226+00:00",
      "daily_context_present": true,
      "public_note": "Crawlable Atlas symbol page backed by daily context metadata.",
      "quality_status": "validated",
      "sitemap_lastmod": "2026-06-16",
      "source_count": 4,
      "symbol": "NFLX",
      "url": "https://atlas.freedomcore.io/stocks/NFLX/"
    },
    {
      "asset_class": "commodity",
      "context_as_of": "2026-06-18T05:03:45.085690+00:00",
      "daily_context_present": true,
      "public_note": "Crawlable Atlas symbol page backed by daily context metadata.",
      "quality_status": "persisted_atlas_wit_v2",
      "sitemap_lastmod": "2026-06-16",
      "source_count": 3,
      "symbol": "NGAS",
      "url": "https://atlas.freedomcore.io/stocks/NGAS/"
    },
    {
      "asset_class": "crypto",
      "context_as_of": "2026-06-18T05:01:05.244284+00:00",
      "daily_context_present": true,
      "public_note": "Crawlable Atlas symbol page backed by daily context metadata.",
      "quality_status": "validated",
      "sitemap_lastmod": "2026-06-16",
      "source_count": 5,
      "symbol": "NIGHT",
      "url": "https://atlas.freedomcore.io/stocks/NIGHT/"
    },
    {
      "asset_class": "equity",
      "context_as_of": "2026-06-18T05:02:32.571334+00:00",
      "daily_context_present": true,
      "public_note": "Crawlable Atlas symbol page backed by daily context metadata.",
      "quality_status": "validated",
      "sitemap_lastmod": "2026-06-16",
      "source_count": 4,
      "symbol": "NKE",
      "url": "https://atlas.freedomcore.io/stocks/NKE/"
    },
    {
      "asset_class": "equity",
      "context_as_of": "2026-06-17T05:32:52.221201+00:00",
      "daily_context_present": true,
      "public_note": "Crawlable Atlas symbol page backed by daily context metadata.",
      "quality_status": "validated",
      "sitemap_lastmod": "2026-06-16",
      "source_count": 4,
      "symbol": "NOW",
      "url": "https://atlas.freedomcore.io/stocks/NOW/"
    },
    {
      "asset_class": "equity",
      "context_as_of": "2026-06-17T05:32:19.152700+00:00",
      "daily_context_present": true,
      "public_note": "Crawlable Atlas symbol page backed by daily context metadata.",
      "quality_status": "persisted_atlas_wit_v2",
      "sitemap_lastmod": "2026-06-16",
      "source_count": 4,
      "symbol": "NVDA",
      "url": "https://atlas.freedomcore.io/stocks/NVDA/"
    },
    {
      "asset_class": "crypto",
      "context_as_of": "2026-06-18T05:00:02.454859+00:00",
      "daily_context_present": true,
      "public_note": "Crawlable Atlas symbol page backed by daily context metadata.",
      "quality_status": "validated",
      "sitemap_lastmod": "2026-06-16",
      "source_count": 4,
      "symbol": "OKB",
      "url": "https://atlas.freedomcore.io/stocks/OKB/"
    },
    {
      "asset_class": "crypto",
      "context_as_of": "2026-06-18T05:00:02.192550+00:00",
      "daily_context_present": true,
      "public_note": "Crawlable Atlas symbol page backed by daily context metadata.",
      "quality_status": "validated",
      "sitemap_lastmod": "2026-06-16",
      "source_count": 5,
      "symbol": "ONDO",
      "url": "https://atlas.freedomcore.io/stocks/ONDO/"
    },
    {
      "asset_class": "equity",
      "context_as_of": "2026-06-18T05:01:45.774422+00:00",
      "daily_context_present": true,
      "public_note": "Crawlable Atlas symbol page backed by daily context metadata.",
      "quality_status": "persisted_atlas_wit_v2",
      "sitemap_lastmod": "2026-06-16",
      "source_count": 4,
      "symbol": "ORCL",
      "url": "https://atlas.freedomcore.io/stocks/ORCL/"
    },
    {
      "asset_class": "commodity",
      "context_as_of": "2026-06-18T05:03:39.534622+00:00",
      "daily_context_present": true,
      "public_note": "Crawlable Atlas symbol page backed by daily context metadata.",
      "quality_status": "persisted_atlas_wit_v2",
      "sitemap_lastmod": "2026-06-16",
      "source_count": 3,
      "symbol": "PALLADIUM",
      "url": "https://atlas.freedomcore.io/stocks/PALLADIUM/"
    },
    {
      "asset_class": "crypto",
      "context_as_of": "2026-06-18T05:00:02.080976+00:00",
      "daily_context_present": true,
      "public_note": "Crawlable Atlas symbol page backed by daily context metadata.",
      "quality_status": "validated",
      "sitemap_lastmod": "2026-06-16",
      "source_count": 5,
      "symbol": "PAXG",
      "url": "https://atlas.freedomcore.io/stocks/PAXG/"
    },
    {
      "asset_class": "crypto",
      "context_as_of": "2026-06-18T05:00:02.841652+00:00",
      "daily_context_present": true,
      "public_note": "Crawlable Atlas symbol page backed by daily context metadata.",
      "quality_status": "validated",
      "sitemap_lastmod": "2026-06-16",
      "source_count": 4,
      "symbol": "PEPE",
      "url": "https://atlas.freedomcore.io/stocks/PEPE/"
    },
    {
      "asset_class": "equity",
      "context_as_of": "2026-06-18T05:02:44.503135+00:00",
      "daily_context_present": true,
      "public_note": "Crawlable Atlas symbol page backed by daily context metadata.",
      "quality_status": "validated",
      "sitemap_lastmod": "2026-06-17",
      "source_count": 4,
      "symbol": "PFE",
      "url": "https://atlas.freedomcore.io/stocks/PFE/"
    },
    {
      "asset_class": "crypto",
      "context_as_of": "2026-06-18T05:00:02.600592+00:00",
      "daily_context_present": true,
      "public_note": "Crawlable Atlas symbol page backed by daily context metadata.",
      "quality_status": "validated",
      "sitemap_lastmod": "2026-06-16",
      "source_count": 5,
      "symbol": "PI",
      "url": "https://atlas.freedomcore.io/stocks/PI/"
    },
    {
      "asset_class": "commodity",
      "context_as_of": "2026-06-18T05:03:41.224637+00:00",
      "daily_context_present": true,
      "public_note": "Crawlable Atlas symbol page backed by daily context metadata.",
      "quality_status": "persisted_atlas_wit_v2",
      "sitemap_lastmod": "2026-06-16",
      "source_count": 3,
      "symbol": "PLATINUM",
      "url": "https://atlas.freedomcore.io/stocks/PLATINUM/"
    },
    {
      "asset_class": "equity",
      "context_as_of": "2026-06-17T05:32:54.184540+00:00",
      "daily_context_present": true,
      "public_note": "Crawlable Atlas symbol page backed by daily context metadata.",
      "quality_status": "persisted_atlas_wit_v2",
      "sitemap_lastmod": "2026-06-16",
      "source_count": 4,
      "symbol": "PLTR",
      "url": "https://atlas.freedomcore.io/stocks/PLTR/"
    },
    {
      "asset_class": "crypto",
      "context_as_of": "2026-06-18T05:01:01.980661+00:00",
      "daily_context_present": true,
      "public_note": "Crawlable Atlas symbol page backed by daily context metadata.",
      "quality_status": "validated",
      "sitemap_lastmod": "2026-06-16",
      "source_count": 5,
      "symbol": "POL",
      "url": "https://atlas.freedomcore.io/stocks/POL/"
    },
    {
      "asset_class": "crypto",
      "context_as_of": "2026-06-18T05:01:03.799937+00:00",
      "daily_context_present": true,
      "public_note": "Crawlable Atlas symbol page backed by daily context metadata.",
      "quality_status": "validated",
      "sitemap_lastmod": "2026-06-16",
      "source_count": 4,
      "symbol": "PUMP",
      "url": "https://atlas.freedomcore.io/stocks/PUMP/"
    },
    {
      "asset_class": "equity",
      "context_as_of": "2026-06-17T17:53:12.212889+00:00",
      "daily_context_present": true,
      "public_note": "Crawlable Atlas symbol page backed by daily context metadata.",
      "quality_status": "validated",
      "sitemap_lastmod": "2026-06-17",
      "source_count": 4,
      "symbol": "PYPL",
      "url": "https://atlas.freedomcore.io/stocks/PYPL/"
    },
    {
      "asset_class": "crypto",
      "context_as_of": "2026-06-18T05:00:01.782583+00:00",
      "daily_context_present": true,
      "public_note": "Crawlable Atlas symbol page backed by daily context metadata.",
      "quality_status": "validated",
      "sitemap_lastmod": "2026-06-16",
      "source_count": 5,
      "symbol": "PYUSD",
      "url": "https://atlas.freedomcore.io/stocks/PYUSD/"
    },
    {
      "asset_class": "crypto",
      "context_as_of": "2026-06-18T05:00:03.012155+00:00",
      "daily_context_present": true,
      "public_note": "Crawlable Atlas symbol page backed by daily context metadata.",
      "quality_status": "validated",
      "sitemap_lastmod": "2026-06-16",
      "source_count": 5,
      "symbol": "QNT",
      "url": "https://atlas.freedomcore.io/stocks/QNT/"
    },
    {
      "asset_class": "etf",
      "context_as_of": "2026-06-18T05:03:17.217194+00:00",
      "daily_context_present": true,
      "public_note": "Crawlable Atlas symbol page backed by daily context metadata.",
      "quality_status": "persisted_atlas_wit_v2",
      "sitemap_lastmod": "2026-06-16",
      "source_count": 3,
      "symbol": "QQQ",
      "url": "https://atlas.freedomcore.io/stocks/QQQ/"
    },
    {
      "asset_class": "crypto",
      "context_as_of": "2026-06-18T05:00:00.993300+00:00",
      "daily_context_present": true,
      "public_note": "Crawlable Atlas symbol page backed by daily context metadata.",
      "quality_status": "validated",
      "sitemap_lastmod": "2026-06-16",
      "source_count": 5,
      "symbol": "RAIN",
      "url": "https://atlas.freedomcore.io/stocks/RAIN/"
    },
    {
      "asset_class": "equity",
      "context_as_of": "2026-06-18T05:03:10.535826+00:00",
      "daily_context_present": true,
      "public_note": "Crawlable Atlas symbol page backed by daily context metadata.",
      "quality_status": "too_few_model_wit_paragraphs",
      "sitemap_lastmod": "2026-06-17",
      "source_count": 4,
      "symbol": "RDDT",
      "url": "https://atlas.freedomcore.io/stocks/RDDT/"
    },
    {
      "asset_class": "crypto",
      "context_as_of": "2026-06-18T05:00:03.171955+00:00",
      "daily_context_present": true,
      "public_note": "Crawlable Atlas symbol page backed by daily context metadata.",
      "quality_status": "validated",
      "sitemap_lastmod": "2026-06-16",
      "source_count": 5,
      "symbol": "RENDER",
      "url": "https://atlas.freedomcore.io/stocks/RENDER/"
    },
    {
      "asset_class": "crypto",
      "context_as_of": "2026-06-18T05:00:02.339158+00:00",
      "daily_context_present": true,
      "public_note": "Crawlable Atlas symbol page backed by daily context metadata.",
      "quality_status": "validated",
      "sitemap_lastmod": "2026-06-16",
      "source_count": 5,
      "symbol": "RLUSD",
      "url": "https://atlas.freedomcore.io/stocks/RLUSD/"
    },
    {
      "asset_class": "equity",
      "context_as_of": "2026-06-17T05:33:31.725629+00:00",
      "daily_context_present": true,
      "public_note": "Crawlable Atlas symbol page backed by daily context metadata.",
      "quality_status": "validated",
      "sitemap_lastmod": "2026-06-16",
      "source_count": 4,
      "symbol": "SBUX",
      "url": "https://atlas.freedomcore.io/stocks/SBUX/"
    },
    {
      "asset_class": "crypto",
      "context_as_of": "2026-06-18T05:00:01.572474+00:00",
      "daily_context_present": true,
      "public_note": "Crawlable Atlas symbol page backed by daily context metadata.",
      "quality_status": "validated",
      "sitemap_lastmod": "2026-06-16",
      "source_count": 5,
      "symbol": "SHIB",
      "url": "https://atlas.freedomcore.io/stocks/SHIB/"
    },
    {
      "asset_class": "commodity",
      "context_as_of": "2026-06-18T05:03:36.146845+00:00",
      "daily_context_present": true,
      "public_note": "Crawlable Atlas symbol page backed by daily context metadata.",
      "quality_status": "persisted_atlas_wit_v2",
      "sitemap_lastmod": "2026-06-16",
      "source_count": 3,
      "symbol": "SILVER",
      "url": "https://atlas.freedomcore.io/stocks/SILVER/"
    },
    {
      "asset_class": "crypto",
      "context_as_of": "2026-06-10T05:00:03.964402+00:00",
      "daily_context_present": true,
      "public_note": "Crawlable Atlas symbol page backed by daily context metadata.",
      "quality_status": "persisted_atlas_wit_v2",
      "sitemap_lastmod": "2026-06-16",
      "source_count": 4,
      "symbol": "SIREN",
      "url": "https://atlas.freedomcore.io/stocks/SIREN/"
    },
    {
      "asset_class": "crypto",
      "context_as_of": "2026-06-18T05:00:02.704968+00:00",
      "daily_context_present": true,
      "public_note": "Crawlable Atlas symbol page backed by daily context metadata.",
      "quality_status": "validated",
      "sitemap_lastmod": "2026-06-16",
      "source_count": 5,
      "symbol": "SKY",
      "url": "https://atlas.freedomcore.io/stocks/SKY/"
    },
    {
      "asset_class": "crypto",
      "context_as_of": "2026-06-18T05:00:00.844561+00:00",
      "daily_context_present": true,
      "public_note": "Crawlable Atlas symbol page backed by daily context metadata.",
      "quality_status": "validated",
      "sitemap_lastmod": "2026-06-16",
      "source_count": 5,
      "symbol": "SOL",
      "url": "https://atlas.freedomcore.io/stocks/SOL/"
    },
    {
      "asset_class": "etf",
      "context_as_of": "2026-06-18T05:01:12.206839+00:00",
      "daily_context_present": true,
      "public_note": "Crawlable Atlas symbol page backed by daily context metadata.",
      "quality_status": "persisted_atlas_wit_v2",
      "sitemap_lastmod": "2026-06-16",
      "source_count": 3,
      "symbol": "SPY",
      "url": "https://atlas.freedomcore.io/stocks/SPY/"
    },
    {
      "asset_class": "crypto",
      "context_as_of": "2026-06-18T05:01:01.924438+00:00",
      "daily_context_present": true,
      "public_note": "Crawlable Atlas symbol page backed by daily context metadata.",
      "quality_status": "validated",
      "sitemap_lastmod": "2026-06-16",
      "source_count": 5,
      "symbol": "STABLE",
      "url": "https://atlas.freedomcore.io/stocks/STABLE/"
    },
    {
      "asset_class": "crypto",
      "context_as_of": "2026-06-18T05:00:01.445772+00:00",
      "daily_context_present": true,
      "public_note": "Crawlable Atlas symbol page backed by daily context metadata.",
      "quality_status": "validated",
      "sitemap_lastmod": "2026-06-16",
      "source_count": 5,
      "symbol": "SUI",
      "url": "https://atlas.freedomcore.io/stocks/SUI/"
    },
    {
      "asset_class": "equity",
      "context_as_of": "2026-06-18T05:03:06.029680+00:00",
      "daily_context_present": true,
      "public_note": "Crawlable Atlas symbol page backed by daily context metadata.",
      "quality_status": "too_few_model_wit_paragraphs",
      "sitemap_lastmod": "2026-06-17",
      "source_count": 4,
      "symbol": "T",
      "url": "https://atlas.freedomcore.io/stocks/T/"
    },
    {
      "asset_class": "crypto",
      "context_as_of": "2026-06-18T05:00:01.910072+00:00",
      "daily_context_present": true,
      "public_note": "Crawlable Atlas symbol page backed by daily context metadata.",
      "quality_status": "validated",
      "sitemap_lastmod": "2026-06-16",
      "source_count": 5,
      "symbol": "TAO",
      "url": "https://atlas.freedomcore.io/stocks/TAO/"
    },
    {
      "asset_class": "crypto",
      "context_as_of": "2026-06-18T05:00:01.206579+00:00",
      "daily_context_present": true,
      "public_note": "Crawlable Atlas symbol page backed by daily context metadata.",
      "quality_status": "validated",
      "sitemap_lastmod": "2026-06-16",
      "source_count": 5,
      "symbol": "TON",
      "url": "https://atlas.freedomcore.io/stocks/TON/"
    },
    {
      "asset_class": "crypto",
      "context_as_of": "2026-06-18T05:00:00.870258+00:00",
      "daily_context_present": true,
      "public_note": "Crawlable Atlas symbol page backed by daily context metadata.",
      "quality_status": "validated",
      "sitemap_lastmod": "2026-06-16",
      "source_count": 5,
      "symbol": "TRX",
      "url": "https://atlas.freedomcore.io/stocks/TRX/"
    },
    {
      "asset_class": "equity",
      "context_as_of": "2026-06-17T05:32:33.702084+00:00",
      "daily_context_present": true,
      "public_note": "Crawlable Atlas symbol page backed by daily context metadata.",
      "quality_status": "persisted_atlas_wit_v2",
      "sitemap_lastmod": "2026-06-16",
      "source_count": 4,
      "symbol": "TSLA",
      "url": "https://atlas.freedomcore.io/stocks/TSLA/"
    },
    {
      "asset_class": "equity",
      "context_as_of": "2026-06-18T05:01:38.478721+00:00",
      "daily_context_present": true,
      "public_note": "Crawlable Atlas symbol page backed by daily context metadata.",
      "quality_status": "persisted_atlas_wit_v2",
      "sitemap_lastmod": "2026-06-16",
      "source_count": 3,
      "symbol": "TSM",
      "url": "https://atlas.freedomcore.io/stocks/TSM/"
    },
    {
      "asset_class": "crypto",
      "context_as_of": "2026-06-18T05:00:03.046718+00:00",
      "daily_context_present": true,
      "public_note": "Crawlable Atlas symbol page backed by daily context metadata.",
      "quality_status": "validated",
      "sitemap_lastmod": "2026-06-16",
      "source_count": 4,
      "symbol": "U",
      "url": "https://atlas.freedomcore.io/stocks/U/"
    },
    {
      "asset_class": "equity",
      "context_as_of": "2026-06-18T05:03:13.016140+00:00",
      "daily_context_present": true,
      "public_note": "Crawlable Atlas symbol page backed by daily context metadata.",
      "quality_status": "validated",
      "sitemap_lastmod": "2026-06-17",
      "source_count": 4,
      "symbol": "UBER",
      "url": "https://atlas.freedomcore.io/stocks/UBER/"
    },
    {
      "asset_class": "index",
      "context_as_of": "2026-06-18T05:03:51.039149+00:00",
      "daily_context_present": true,
      "public_note": "Crawlable Atlas symbol page backed by daily context metadata.",
      "quality_status": "validated",
      "sitemap_lastmod": "2026-06-16",
      "source_count": 2,
      "symbol": "UK100",
      "url": "https://atlas.freedomcore.io/stocks/UK100/"
    },
    {
      "asset_class": "commodity",
      "context_as_of": "2026-06-18T05:01:16.044797+00:00",
      "daily_context_present": true,
      "public_note": "Crawlable Atlas symbol page backed by daily context metadata.",
      "quality_status": "persisted_atlas_wit_v2",
      "sitemap_lastmod": "2026-06-16",
      "source_count": 3,
      "symbol": "UKOIL",
      "url": "https://atlas.freedomcore.io/stocks/UKOIL/"
    },
    {
      "asset_class": "equity",
      "context_as_of": "2026-06-18T05:02:39.665107+00:00",
      "daily_context_present": true,
      "public_note": "Crawlable Atlas symbol page backed by daily context metadata.",
      "quality_status": "validated",
      "sitemap_lastmod": "2026-06-16",
      "source_count": 4,
      "symbol": "UNH",
      "url": "https://atlas.freedomcore.io/stocks/UNH/"
    },
    {
      "asset_class": "crypto",
      "context_as_of": "2026-06-18T05:00:02.423324+00:00",
      "daily_context_present": true,
      "public_note": "Crawlable Atlas symbol page backed by daily context metadata.",
      "quality_status": "validated",
      "sitemap_lastmod": "2026-06-16",
      "source_count": 5,
      "symbol": "UNI",
      "url": "https://atlas.freedomcore.io/stocks/UNI/"
    },
    {
      "asset_class": "crypto",
      "context_as_of": "2026-06-18T05:01:03.744305+00:00",
      "daily_context_present": true,
      "public_note": "Crawlable Atlas symbol page backed by daily context metadata.",
      "quality_status": "validated",
      "sitemap_lastmod": "2026-06-16",
      "source_count": 5,
      "symbol": "USD0",
      "url": "https://atlas.freedomcore.io/stocks/USD0/"
    },
    {
      "asset_class": "crypto",
      "context_as_of": "2026-06-18T05:00:01.277250+00:00",
      "daily_context_present": true,
      "public_note": "Crawlable Atlas symbol page backed by daily context metadata.",
      "quality_status": "validated",
      "sitemap_lastmod": "2026-06-16",
      "source_count": 4,
      "symbol": "USD1",
      "url": "https://atlas.freedomcore.io/stocks/USD1/"
    },
    {
      "asset_class": "crypto",
      "context_as_of": "2026-06-18T05:00:00.802786+00:00",
      "daily_context_present": true,
      "public_note": "Crawlable Atlas symbol page backed by daily context metadata.",
      "quality_status": "validated",
      "sitemap_lastmod": "2026-06-16",
      "source_count": 5,
      "symbol": "USDC",
      "url": "https://atlas.freedomcore.io/stocks/USDC/"
    },
    {
      "asset_class": "crypto",
      "context_as_of": "2026-06-18T05:00:02.673569+00:00",
      "daily_context_present": true,
      "public_note": "Crawlable Atlas symbol page backed by daily context metadata.",
      "quality_status": "validated",
      "sitemap_lastmod": "2026-06-16",
      "source_count": 5,
      "symbol": "USDD",
      "url": "https://atlas.freedomcore.io/stocks/USDD/"
    },
    {
      "asset_class": "crypto",
      "context_as_of": "2026-06-18T05:00:01.224640+00:00",
      "daily_context_present": true,
      "public_note": "Crawlable Atlas symbol page backed by daily context metadata.",
      "quality_status": "validated",
      "sitemap_lastmod": "2026-06-16",
      "source_count": 5,
      "symbol": "USDE",
      "url": "https://atlas.freedomcore.io/stocks/USDE/"
    },
    {
      "asset_class": "crypto",
      "context_as_of": "2026-06-18T05:00:02.554649+00:00",
      "daily_context_present": true,
      "public_note": "Crawlable Atlas symbol page backed by daily context metadata.",
      "quality_status": "validated",
      "sitemap_lastmod": "2026-06-16",
      "source_count": 5,
      "symbol": "USDF",
      "url": "https://atlas.freedomcore.io/stocks/USDF/"
    },
    {
      "asset_class": "crypto",
      "context_as_of": "2026-06-18T05:00:01.878210+00:00",
      "daily_context_present": true,
      "public_note": "Crawlable Atlas symbol page backed by daily context metadata.",
      "quality_status": "validated",
      "sitemap_lastmod": "2026-06-16",
      "source_count": 5,
      "symbol": "USDG",
      "url": "https://atlas.freedomcore.io/stocks/USDG/"
    },
    {
      "asset_class": "forex",
      "context_as_of": "2026-06-18T05:03:32.299796+00:00",
      "daily_context_present": true,
      "public_note": "Crawlable Atlas symbol page backed by daily context metadata.",
      "quality_status": "persisted_atlas_wit_v2",
      "sitemap_lastmod": "2026-06-16",
      "source_count": 5,
      "symbol": "USDJPY",
      "url": "https://atlas.freedomcore.io/stocks/USDJPY/"
    },
    {
      "asset_class": "crypto",
      "context_as_of": "2026-06-18T05:00:00.955025+00:00",
      "daily_context_present": true,
      "public_note": "Crawlable Atlas symbol page backed by daily context metadata.",
      "quality_status": "validated",
      "sitemap_lastmod": "2026-06-16",
      "source_count": 5,
      "symbol": "USDS",
      "url": "https://atlas.freedomcore.io/stocks/USDS/"
    },
    {
      "asset_class": "crypto",
      "context_as_of": "2026-06-18T05:00:00.758776+00:00",
      "daily_context_present": true,
      "public_note": "Crawlable Atlas symbol page backed by daily context metadata.",
      "quality_status": "validated",
      "sitemap_lastmod": "2026-06-16",
      "source_count": 5,
      "symbol": "USDT",
      "url": "https://atlas.freedomcore.io/stocks/USDT/"
    },
    {
      "asset_class": "crypto",
      "context_as_of": "2026-06-18T05:00:03.365643+00:00",
      "daily_context_present": true,
      "public_note": "Crawlable Atlas symbol page backed by daily context metadata.",
      "quality_status": "validated",
      "sitemap_lastmod": "2026-06-16",
      "source_count": 5,
      "symbol": "USDTB",
      "url": "https://atlas.freedomcore.io/stocks/USDTB/"
    },
    {
      "asset_class": "crypto",
      "context_as_of": "2026-06-18T05:00:01.969499+00:00",
      "daily_context_present": true,
      "public_note": "Crawlable Atlas symbol page backed by daily context metadata.",
      "quality_status": "validated",
      "sitemap_lastmod": "2026-06-16",
      "source_count": 5,
      "symbol": "USDY",
      "url": "https://atlas.freedomcore.io/stocks/USDY/"
    },
    {
      "asset_class": "commodity",
      "context_as_of": "2026-06-18T05:03:43.026572+00:00",
      "daily_context_present": true,
      "public_note": "Crawlable Atlas symbol page backed by daily context metadata.",
      "quality_status": "persisted_atlas_wit_v2",
      "sitemap_lastmod": "2026-06-16",
      "source_count": 3,
      "symbol": "USOIL",
      "url": "https://atlas.freedomcore.io/stocks/USOIL/"
    },
    {
      "asset_class": "crypto",
      "context_as_of": "2026-06-18T05:00:03.153975+00:00",
      "daily_context_present": true,
      "public_note": "Crawlable Atlas symbol page backed by daily context metadata.",
      "quality_status": "validated",
      "sitemap_lastmod": "2026-06-16",
      "source_count": 5,
      "symbol": "USTB",
      "url": "https://atlas.freedomcore.io/stocks/USTB/"
    },
    {
      "asset_class": "crypto",
      "context_as_of": "2026-06-11T05:01:08.070216+00:00",
      "daily_context_present": true,
      "public_note": "Crawlable Atlas symbol page backed by daily context metadata.",
      "quality_status": "persisted_atlas_wit_v2",
      "sitemap_lastmod": "2026-06-16",
      "source_count": 5,
      "symbol": "USX",
      "url": "https://atlas.freedomcore.io/stocks/USX/"
    },
    {
      "asset_class": "crypto",
      "context_as_of": "2026-06-18T05:00:01.542437+00:00",
      "daily_context_present": true,
      "public_note": "Crawlable Atlas symbol page backed by daily context metadata.",
      "quality_status": "validated",
      "sitemap_lastmod": "2026-06-16",
      "source_count": 5,
      "symbol": "USYC",
      "url": "https://atlas.freedomcore.io/stocks/USYC/"
    },
    {
      "asset_class": "equity",
      "context_as_of": "2026-06-18T05:02:11.594329+00:00",
      "daily_context_present": true,
      "public_note": "Crawlable Atlas symbol page backed by daily context metadata.",
      "quality_status": "validated",
      "sitemap_lastmod": "2026-06-16",
      "source_count": 4,
      "symbol": "V",
      "url": "https://atlas.freedomcore.io/stocks/V/"
    },
    {
      "asset_class": "crypto",
      "context_as_of": "2026-06-14T05:00:03.488986+00:00",
      "daily_context_present": true,
      "public_note": "Crawlable Atlas symbol page backed by daily context metadata.",
      "quality_status": "persisted_atlas_wit_v2",
      "sitemap_lastmod": "2026-06-16",
      "source_count": 5,
      "symbol": "VELVET",
      "url": "https://atlas.freedomcore.io/stocks/VELVET/"
    },
    {
      "asset_class": "index",
      "context_as_of": "2026-06-18T05:03:47.602129+00:00",
      "daily_context_present": true,
      "public_note": "Crawlable Atlas symbol page backed by daily context metadata.",
      "quality_status": "validated",
      "sitemap_lastmod": "2026-06-16",
      "source_count": 2,
      "symbol": "VIX",
      "url": "https://atlas.freedomcore.io/stocks/VIX/"
    },
    {
      "asset_class": "crypto",
      "context_as_of": "2026-06-18T05:01:02.044828+00:00",
      "daily_context_present": true,
      "public_note": "Crawlable Atlas symbol page backed by daily context metadata.",
      "quality_status": "validated",
      "sitemap_lastmod": "2026-06-16",
      "source_count": 4,
      "symbol": "VVV",
      "url": "https://atlas.freedomcore.io/stocks/VVV/"
    },
    {
      "asset_class": "equity",
      "context_as_of": "2026-06-17T05:33:59.852494+00:00",
      "daily_context_present": true,
      "public_note": "Crawlable Atlas symbol page backed by daily context metadata.",
      "quality_status": "validated",
      "sitemap_lastmod": "2026-06-16",
      "source_count": 4,
      "symbol": "VZ",
      "url": "https://atlas.freedomcore.io/stocks/VZ/"
    },
    {
      "asset_class": "crypto",
      "context_as_of": "2026-06-18T05:00:01.124886+00:00",
      "daily_context_present": true,
      "public_note": "Crawlable Atlas symbol page backed by daily context metadata.",
      "quality_status": "validated",
      "sitemap_lastmod": "2026-06-16",
      "source_count": 5,
      "symbol": "WBT",
      "url": "https://atlas.freedomcore.io/stocks/WBT/"
    },
    {
      "asset_class": "equity",
      "context_as_of": "2026-06-17T05:33:01.198421+00:00",
      "daily_context_present": true,
      "public_note": "Crawlable Atlas symbol page backed by daily context metadata.",
      "quality_status": "persisted_atlas_wit_v2",
      "sitemap_lastmod": "2026-06-16",
      "source_count": 4,
      "symbol": "WFC",
      "url": "https://atlas.freedomcore.io/stocks/WFC/"
    },
    {
      "asset_class": "crypto",
      "context_as_of": "2026-06-18T05:00:02.024170+00:00",
      "daily_context_present": true,
      "public_note": "Crawlable Atlas symbol page backed by daily context metadata.",
      "quality_status": "validated",
      "sitemap_lastmod": "2026-06-16",
      "source_count": 5,
      "symbol": "WLD",
      "url": "https://atlas.freedomcore.io/stocks/WLD/"
    },
    {
      "asset_class": "crypto",
      "context_as_of": "2026-06-18T05:00:02.106033+00:00",
      "daily_context_present": true,
      "public_note": "Crawlable Atlas symbol page backed by daily context metadata.",
      "quality_status": "validated",
      "sitemap_lastmod": "2026-06-16",
      "source_count": 5,
      "symbol": "WLFI",
      "url": "https://atlas.freedomcore.io/stocks/WLFI/"
    },
    {
      "asset_class": "equity",
      "context_as_of": "2026-06-17T05:33:21.221148+00:00",
      "daily_context_present": true,
      "public_note": "Crawlable Atlas symbol page backed by daily context metadata.",
      "quality_status": "persisted_atlas_wit_v2",
      "sitemap_lastmod": "2026-06-16",
      "source_count": 4,
      "symbol": "WMT",
      "url": "https://atlas.freedomcore.io/stocks/WMT/"
    },
    {
      "asset_class": "crypto",
      "context_as_of": "2026-06-18T05:00:01.895019+00:00",
      "daily_context_present": true,
      "public_note": "Crawlable Atlas symbol page backed by daily context metadata.",
      "quality_status": "validated",
      "sitemap_lastmod": "2026-06-16",
      "source_count": 5,
      "symbol": "XAUT",
      "url": "https://atlas.freedomcore.io/stocks/XAUT/"
    },
    {
      "asset_class": "crypto",
      "context_as_of": "2026-06-18T05:01:03.634091+00:00",
      "daily_context_present": true,
      "public_note": "Crawlable Atlas symbol page backed by daily context metadata.",
      "quality_status": "validated",
      "sitemap_lastmod": "2026-06-16",
      "source_count": 5,
      "symbol": "XDC",
      "url": "https://atlas.freedomcore.io/stocks/XDC/"
    },
    {
      "asset_class": "crypto",
      "context_as_of": "2026-06-18T05:00:01.077347+00:00",
      "daily_context_present": true,
      "public_note": "Crawlable Atlas symbol page backed by daily context metadata.",
      "quality_status": "validated",
      "sitemap_lastmod": "2026-06-16",
      "source_count": 5,
      "symbol": "XLM",
      "url": "https://atlas.freedomcore.io/stocks/XLM/"
    },
    {
      "asset_class": "crypto",
      "context_as_of": "2026-06-18T05:00:01.145028+00:00",
      "daily_context_present": true,
      "public_note": "Crawlable Atlas symbol page backed by daily context metadata.",
      "quality_status": "validated",
      "sitemap_lastmod": "2026-06-16",
      "source_count": 5,
      "symbol": "XMR",
      "url": "https://atlas.freedomcore.io/stocks/XMR/"
    },
    {
      "asset_class": "equity",
      "context_as_of": "2026-06-18T05:02:48.962184+00:00",
      "daily_context_present": true,
      "public_note": "Crawlable Atlas symbol page backed by daily context metadata.",
      "quality_status": "validated",
      "sitemap_lastmod": "2026-06-16",
      "source_count": 4,
      "symbol": "XOM",
      "url": "https://atlas.freedomcore.io/stocks/XOM/"
    },
    {
      "asset_class": "crypto",
      "context_as_of": "2026-06-18T05:00:00.818923+00:00",
      "daily_context_present": true,
      "public_note": "Crawlable Atlas symbol page backed by daily context metadata.",
      "quality_status": "validated",
      "sitemap_lastmod": "2026-06-16",
      "source_count": 5,
      "symbol": "XRP",
      "url": "https://atlas.freedomcore.io/stocks/XRP/"
    },
    {
      "asset_class": "equity",
      "context_as_of": "2026-06-17T17:55:29.394617+00:00",
      "daily_context_present": true,
      "public_note": "Crawlable Atlas symbol page backed by daily context metadata.",
      "quality_status": "validated",
      "sitemap_lastmod": "2026-06-17",
      "source_count": 4,
      "symbol": "XYZ",
      "url": "https://atlas.freedomcore.io/stocks/XYZ/"
    },
    {
      "asset_class": "crypto",
      "context_as_of": "2026-06-18T05:01:03.727711+00:00",
      "daily_context_present": true,
      "public_note": "Crawlable Atlas symbol page backed by daily context metadata.",
      "quality_status": "validated",
      "sitemap_lastmod": "2026-06-16",
      "source_count": 4,
      "symbol": "YLDS",
      "url": "https://atlas.freedomcore.io/stocks/YLDS/"
    },
    {
      "asset_class": "crypto",
      "context_as_of": "2026-06-18T05:00:01.016747+00:00",
      "daily_context_present": true,
      "public_note": "Crawlable Atlas symbol page backed by daily context metadata.",
      "quality_status": "validated",
      "sitemap_lastmod": "2026-06-16",
      "source_count": 5,
      "symbol": "ZEC",
      "url": "https://atlas.freedomcore.io/stocks/ZEC/"
    }
  ],
  "schema": "atlas.symbol_coverage.v1"
}
